{
    "admin": {
        "listen": "0.0.0.0:2019"
    },
    "apps": {
        "http": {
            "servers": {
                "localhost:80": {
                    "listen": [
                        ":80"
                    ],
                    "routes": [
                        {
                            "match": [
                                {
                                    "path": [
                                        "*"
                                    ]
                                }
                            ],
                            "handle": [
                                {
                                    "handler": "file_server"
                                }
                            ]
                        }
                    ]
                }
            }
        }
    }
}